_FaustCorePy.cpython-312-x86_64-linux-gnu.so
pyfaust/__init__.py
pyfaust/datadl.py
pyfaust/demo.py
pyfaust/fact.py
pyfaust/factparams.py
pyfaust/license.txt
pyfaust/license_hdf5.txt
pyfaust/license_matio.txt
pyfaust/license_openblas.txt
pyfaust/license_scipy.txt
pyfaust/license_zlib.txt
pyfaust/logo.py
pyfaust/poly.py
pyfaust/proj.py
pyfaust/tools.py
pyfaust/fdb/GB_factorization.py
pyfaust/fdb/GB_operators.py
pyfaust/fdb/GB_param_generate.py
pyfaust/fdb/utils.py
pyfaust/lib/libgfortran.so
pyfaust/lib/libgm-cu11.4.so
pyfaust/lib/libgm-cu12.1.so
pyfaust/lib/libomp.so
pyfaust/lib/libopenblaso.so
pyfaust/tests/TestFact.py
pyfaust/tests/TestFactParams.py
pyfaust/tests/TestFaust.py
pyfaust/tests/TestPoly.py
pyfaust/tests/__init__.py
pyfaust/tests/run.py
pyfaust_openblaso-3.42.1.dist-info/METADATA
pyfaust_openblaso-3.42.1.dist-info/WHEEL
pyfaust_openblaso-3.42.1.dist-info/top_level.txt
pyfaust_openblaso-3.42.1.dist-info/RECORD
