Metadata-Version: 2.1
Name: pyfaust-openblaso
Version: 3.42.1
Summary: FAµST python toolbox
Home-page: https://faust.inria.fr
Author: Inria, Rémi Gribonval et al.
Author-email: remi.gribonval@inria.fr
Maintainer-email: hakim.hadj-djilani@inria.fr
License: BSD-3-clause
Project-URL: Bug Tracker, https://gitlab.inria.fr/faustgrp/faust/-/issues
Project-URL: Documentation, https://faust.inria.fr/api-doc/
Project-URL: Source Code, https://gitlab.inria.fr/faustgrp/faust
Platform: Windows
Platform: Linux
Platform: Mac OS-X
Classifier: License :: OSI Approved :: BSD License
Classifier: Programming Language :: Python :: 3.11
Classifier: Programming Language :: Python :: 3.12
Classifier: Programming Language :: Python :: 3.13
Classifier: Environment :: GPU :: NVIDIA CUDA :: 12
Classifier: Environment :: GPU :: NVIDIA CUDA :: 11
Classifier: Development Status :: 5 - Production/Stable
Classifier: Intended Audience :: Science/Research
Classifier: Intended Audience :: Developers
Classifier: License :: OSI Approved :: BSD License
Classifier: Programming Language :: C
Classifier: Programming Language :: C++
Classifier: Topic :: Software Development
Classifier: Topic :: Scientific/Engineering
Classifier: Operating System :: Microsoft :: Windows
Classifier: Operating System :: POSIX
Classifier: Operating System :: Unix
Classifier: Operating System :: MacOS
Requires-Dist: scipy
Requires-Dist: numpy >=2.0.0
Requires-Dist: matplotlib >=2.0.0
